contextlib2.py
contextlib2-0.5.2.dist-info/DESCRIPTION.rst
contextlib2-0.5.2.dist-info/METADATA
contextlib2-0.5.2.dist-info/RECORD
contextlib2-0.5.2.dist-info/WHEEL
contextlib2-0.5.2.dist-info/metadata.json
contextlib2-0.5.2.dist-info/top_level.txt
