Metadata-Version: 1.1
Name: contextlib2
Version: 0.5.2
Summary: Backports and enhancements for the contextlib module
Home-page: http://contextlib2.readthedocs.org
Author: Nick Coghlan
Author-email: ncoghlan@gmail.com
License: PSF License
Platform: UNKNOWN
Classifier: Development Status :: 5 - Production/Stable
Classifier: License :: OSI Approved :: Python Software Foundation License
Classifier: Programming Language :: Python :: 2
Classifier: Programming Language :: Python :: 2.7
Classifier: Programming Language :: Python :: 3
Classifier: Programming Language :: Python :: 3.4
Classifier: Programming Language :: Python :: 3.5
